django_secret_settings/__init__.py
django_secret_settings/autoload.py
django_secret_settings/error.py
django_secret_settings/django/__init__.py
django_secret_settings/django/error.py
django_secret_settings/django/settings_manager.py
django_secret_settings/store/__init__.py
django_secret_settings/store/crypto.py
django_secret_settings/store/error.py
django_secret_settings/store/factory.py
django_secret_settings/store/secret_store.py
tests/__init__.py
tests/integrationtests/__init__.py
tests/integrationtests/test_autoload.py
tests/integrationtests/settings_fixtures/__init__.py
tests/integrationtests/settings_fixtures/empty/__init__.py
tests/integrationtests/settings_fixtures/encrypted/__init__.py
tests/integrationtests/settings_fixtures/encrypted/production.py
tests/integrationtests/settings_fixtures/missing_module/__init__.py
tests/integrationtests/settings_fixtures/missing_secret_file/__init__.py
tests/integrationtests/settings_fixtures/missing_secret_file/production.py
tests/integrationtests/settings_fixtures/missing_secret_key/__init__.py
tests/integrationtests/settings_fixtures/missing_secret_key/production.py
tests/integrationtests/settings_fixtures/no_private_key/__init__.py
tests/integrationtests/settings_fixtures/two_private_keys/__init__.py
tests/integrationtests/settings_fixtures/unencrypted/__init__.py
tests/integrationtests/settings_fixtures/unencrypted/development.py
tests/unittests/__init__.py
tests/unittests/test_autoload.py
tests/unittests/django/__init__.py
tests/unittests/django/test_settings_manager.py
tests/unittests/store/__init__.py
tests/unittests/store/test_crypto.py
tests/unittests/store/test_factory.py
tests/unittests/store/test_secret_store.py
django_secret_settings-1.0.0.dist-info/LICENSE
django_secret_settings-1.0.0.dist-info/METADATA
django_secret_settings-1.0.0.dist-info/WHEEL
django_secret_settings-1.0.0.dist-info/top_level.txt
django_secret_settings-1.0.0.dist-info/RECORD
