Metadata-Version: 2.1
Name: django-secret-settings
Version: 1.0.0
Summary: A Python package facilitating the inclusion of encrypted secrets in the Django settings.
Home-page: https://gitlab.com/cmahr/django-secret-settings
Author: Carsten E. Mahr
Author-email: impressum@carsten-mahr.de
License: http://www.apache.org/licenses/LICENSE-2.0
Platform: UNKNOWN
Classifier: Environment :: Web Environment
Classifier: Framework :: Django
Classifier: Framework :: Django :: 2.1
Classifier: Framework :: Django :: 2.2
Classifier: Intended Audience :: Developers
Classifier: License :: OSI Approved :: Apache Software License
Classifier: Operating System :: POSIX :: Linux
Classifier: Programming Language :: Python :: 3 :: Only
Classifier: Programming Language :: Python :: 3.5
Classifier: Programming Language :: Python :: 3.6
Classifier: Topic :: Internet :: WWW/HTTP :: WSGI :: Application
Classifier: Topic :: Security :: Cryptography
